fastapi_websocket_pubsub/__init__.py
fastapi_websocket_pubsub/event_broadcaster.py
fastapi_websocket_pubsub/event_notifier.py
fastapi_websocket_pubsub/exceptions.py
fastapi_websocket_pubsub/logger.py
fastapi_websocket_pubsub/pub_sub_client.py
fastapi_websocket_pubsub/pub_sub_server.py
fastapi_websocket_pubsub/rpc_event_methods.py
fastapi_websocket_pubsub/util.py
fastapi_websocket_pubsub/websocket_rpc_event_notifier.py
fastapi_websocket_pubsub-1.0.1.dist-info/LICENSE
fastapi_websocket_pubsub-1.0.1.dist-info/METADATA
fastapi_websocket_pubsub-1.0.1.dist-info/WHEEL
fastapi_websocket_pubsub-1.0.1.dist-info/top_level.txt
fastapi_websocket_pubsub-1.0.1.dist-info/RECORD
