Metadata-Version: 2.1
Name: fastapi-websocket-pubsub
Version: 1.0.1
Summary: A fast and durable PubSub channel over Websockets (using fastapi-websockets-rpc).
Home-page: https://github.com/permitio/fastapi_websocket_pubsub
Author: Or Weis
Author-email: or@permit.io
Classifier: Programming Language :: Python :: 3
Classifier: License :: OSI Approved :: MIT License
Classifier: Operating System :: OS Independent
Classifier: Topic :: Internet :: WWW/HTTP :: HTTP Servers
Classifier: Topic :: Internet :: WWW/HTTP :: WSGI
Requires-Python: >=3.9
License-File: LICENSE
Requires-Dist: fastapi-websocket-rpc<1,>=0.1.25
Requires-Dist: packaging>=20.4
Requires-Dist: pydantic>=1.9.1
Requires-Dist: websockets>=14.0
Requires-Dist: permit-broadcaster<1,>=0.2.5
Provides-Extra: all
Requires-Dist: permit-broadcaster[kafka,postgres,redis]<1,>=0.2.5; extra == "all"
Provides-Extra: kafka
Requires-Dist: permit-broadcaster[kafka]<1,>=0.2.5; extra == "kafka"
Provides-Extra: postgres
Requires-Dist: permit-broadcaster[postgres]<1,>=0.2.5; extra == "postgres"
Provides-Extra: redis
Requires-Dist: permit-broadcaster[redis]<1,>=0.2.5; extra == "redis"
